q6/Q6/dflipflop2.v
// ROUNAK MODI & VEENA NAGAR
//17CO236 & 17C0151
// 14 oct 2018

module dflipflop(Q,Qn,C,D);
   output Q,Qn;
   input C,D;
  
   wire Cn;   // Control input to the D latch.
   wire DQ;   
   wire DQn;  
   
   not(Cn,C);
   d_latch dl(DQ,DQn,Cn,D);
endmodule 

// D-Latch
module d_latch(Q,Qn,G,D);
   output Q,Qn;
   input G,D;   
   
   wire Dn,D1,Dn1; 
   
   not(Dn,D);   
   and(D1,G, D);
   and(Dn1,G, Dn);   
   nor(Qn,D1,Q);
   nor(Q,Dn1,Qn);
endmodule

q6/Q6/t_dflipflop2.v
// ROUNAK MODI & VEENA NAGAR
//17CO236 & 17C0151
// 14 oct 2018
`timescale 1ns/1ps
module test;
wire Q,Qn;
reg D,C;

dflipflop out(Q, Qn, C, D);
initial begin
		$dumpfile("dflipflop.vcd");    //gtkwave production
		$dumpvars(0, test);
		C=0;                  //clk set
		forever #1 C=~C;
	end
	initial begin                                //value of d set at regular interval and displayed
			D=0;
			$monitor("clock=%b, d=%b, q=%b",C,D,Q);
		#8;
			D=1;
			$monitor("clock=%b, d=%b, q=%b",C,D,Q);
		#8;
			D=0;
			$monitor("clock=%b, d=%b, q=%b",C,D,Q);
		#8;
			D=1;
			$monitor("clock=%b, d=%b, q=%b",C,D,Q);
                
	end
	initial #30 $finish;
endmodule

q6/Q6/dflipflop.vcd
$date
	Mon Oct 15 10:41:23 2018
$end
$version
	Icarus Verilog
$end
$timescale
	1ps
$end
$scope module test $end
$var wire 1 ! Q $end
$var wire 1 " Qn $end
$var reg 1 # C $end
$var reg 1 $ D $end
$scope module out $end
$var wire 1 # C $end
$var wire 1 % Cn $end
$var wire 1 $ D $end
$var wire 1 ! Q $end
$var wire 1 " Qn $end
$var wire 1 & DQn $end
$var wire 1 ' DQ $end
$scope module dl $end
$var wire 1 $ D $end
$var wire 1 ( D1 $end
$var wire 1 ) Dn $end
$var wire 1 * Dn1 $end
$var wire 1 % G $end
$var wire 1 ' Q $end
$var wire 1 & Qn $end
$upscope $end
$upscope $end
$upscope $end
$enddefinitions $end
#0
$dumpvars
1*
1)
0(
0'
1&
1%
0$
0#
z"
z!
$end
#1000
0*
0%
1#
#2000
1*
1%
0#
#3000
0*
0%
1#
#4000
1*
1%
0#
#5000
0*
0%
1#
#6000
1*
1%
0#
#7000
0*
0%
1#
#8000
1'
0&
1(
1%
0)
0#
1$
#9000
0(
0%
1#
#10000
1(
1%
0#
#11000
0(
0%
1#
#12000
1(
1%
0#
#13000
0(
0%
1#
#14000
1(
1%
0#
#15000
0(
0%
1#
#16000
1&
0'
1*
1%
1)
0#
0$
#17000
0*
0%
1#
#18000
1*
1%
0#
#19000
0*
0%
1#
#20000
1*
1%
0#
#21000
0*
0%
1#
#22000
1*
1%
0#
#23000
0*
0%
1#
#24000
1'
0&
1(
1%
0)
0#
1$
#25000
0(
0%
1#
#26000
1(
1%
0#
#27000
0(
0%
1#
#28000
1(
1%
0#
#29000
0(
0%
1#
#30000
1(
1%
0#
