q2/q2_decoder.v
// Veena Nagar 171CO151, Rounak Modi 171CO236
//decoder
//15 october 2018


`timescale 1ns/1ns
module decoder(a,y);
	input [3:0] a;
	output [15:0] y;
	reg [15:0] y;
	
	always @(a)
	begin
		assign 	y[0]=!a[0]&!a[1]&!a[2]&!a[3];
		assign	y[1]=!a[0]&!a[1]&!a[2]&a[3];
		assign	y[2]=!a[0]&!a[1]&a[2]&!a[3];
		assign	y[3]=!a[0]&!a[1]&a[2]&a[3];
		assign	y[4]=!a[0]&a[1]&!a[2]&!a[3];
		assign	y[5]=!a[0]&a[1]&!a[2]&a[3];
		assign	y[6]=!a[0]&a[1]&a[2]&!a[3];
		assign	y[7]=!a[0]&a[1]&a[2]&a[3];
		assign	y[8]=a[0]&!a[1]&!a[2]&!a[3];
		assign	y[9]=a[0]&!a[1]&!a[2]&a[3];
		assign	y[10]=a[0]&!a[1]&a[2]&!a[3];
		assign	y[11]=a[0]&!a[1]&a[2]&a[3];
		assign	y[12]=a[0]&a[1]&!a[2]&!a[3];
		assign	y[13]=a[0]&a[1]&!a[2]&a[3];
		assign	y[14]=a[0]&a[1]&a[2]&!a[3];
		assign	y[15]=a[0]&a[1]&a[2]&a[3];
	end
endmodule

//testbench code

module decoder_tb;
	reg [3:0] a;
	wire [15:0] y;
	
initial begin
	$dumpfile("q2_decoder.vcd");
	$dumpvars(0,decoder_tb);	
	$monitor ("a[0]=%b, a[1]=%b, a[2]=%b, a[3]=%b y[0]=%b",a[0],a[1],a[2],a[3],y[0]);
	a[0]=0;
	a[1]=0;
	a[2]=0;
	a[3]=0;
	
	#10 a[3]=1;
	#10 a[3]=0;
	#10 a[2]=1;
	#10 a[3]=1;
	#10 a[2]=0;
	#10 a[3]=0;
	#10 a[1]=1;
	#10 a[3]=1;
	#10 a[2]=1;
	#10 a[0]=1;
	
	#10 $finish;
end

decoder d(
	.a(a),
	.y(y)
);
endmodule

q2/q2_decoder.vcd
$date
	Mon Oct 15 23:34:45 2018
$end
$version
	Icarus Verilog
$end
$timescale
	1ns
$end
$scope module decoder_tb $end
$var wire 16 ! y [15:0] $end
$var reg 4 " a [3:0] $end
$scope module d $end
$var wire 4 # a [3:0] $end
$var reg 16 $ y [15:0] $end
$upscope $end
$upscope $end
$enddefinitions $end
#0
$dumpvars
b1 $
b0 #
b0 "
b1 !
$end
#10
b10 $
b10 !
b1000 "
b1000 #
#20
b1 $
b1 !
b0 "
b0 #
#30
b100 $
b100 !
b100 "
b100 #
#40
b1000 !
b1000 $
b1100 "
b1100 #
#50
b10 !
b10 $
b1000 "
b1000 #
#60
b1 $
b1 !
b0 "
b0 #
#70
b10000 $
b10000 !
b10 "
b10 #
#80
b100000 !
b100000 $
b1010 "
b1010 #
#90
b10000000 !
b10000000 $
b1110 "
b1110 #
#100
b1000000000000000 !
b1000000000000000 $
b1111 "
b1111 #
