q2/q2_encoder.v
// Veena Nagar 171CO151, Rounak Modi 171CO236
//encoder
//15 october 2018

`timescale 1ns/1ns
module encoder(y,d);
	input [15:0] d;
	output [3:0] y;
	reg [3:0] y;
	
	always @(d)
	begin
		assign	y[3]=d[8]|d[9]|d[10]|d[11]|d[12]|d[13]|d[14]|d[15];
    		assign	y[2]=d[4]|d[5]|d[6]|d[7]|d[12]|d[13]|d[14]|d[15];
    		assign	y[1]=d[2]|d[3]|d[6]|d[7]|d[10]|d[11]|d[14]|d[15];
    		assign	y[0]=d[1]|d[3]|d[5]|d[7]|d[9]|d[11]|d[13]|d[15];
	end
endmodule

//test bench code

module encoder_tb();
	reg [15:0] d;
	wire [3:0] y;
	integer i;
initial begin
	$dumpfile("q2_encoder.vcd");
	$dumpvars(0,encoder_tb);
	
	for(i=0;i<15;i=i+1)
		begin
			d=0;
			d[i]=1;
		#10;
		end
	
#150 $finish;
end

encoder e(
	.y(y),
	.d(d)
);
endmodule

q2/q2_encoder.vcd
$date
	Mon Oct 15 23:42:33 2018
$end
$version
	Icarus Verilog
$end
$timescale
	1ns
$end
$scope module encoder_tb $end
$var wire 4 ! y [3:0] $end
$var reg 16 " d [15:0] $end
$var integer 32 # i [31:0] $end
$scope module e $end
$var wire 16 $ d [15:0] $end
$var reg 4 % y [3:0] $end
$upscope $end
$upscope $end
$enddefinitions $end
#0
$dumpvars
b0 %
b1 $
b0 #
b1 "
b0 !
$end
#10
b1 !
b1 %
b10 "
b10 $
b1 #
#20
b10 !
b10 %
b100 "
b100 $
b10 #
#30
b11 !
b11 %
b1000 "
b1000 $
b11 #
#40
b100 !
b100 %
b10000 "
b10000 $
b100 #
#50
b101 !
b101 %
b100000 "
b100000 $
b101 #
#60
b110 !
b110 %
b1000000 "
b1000000 $
b110 #
#70
b111 !
b111 %
b10000000 "
b10000000 $
b111 #
#80
b1000 %
b1000 !
b100000000 "
b100000000 $
b1000 #
#90
b1001 !
b1001 %
b1000000000 "
b1000000000 $
b1001 #
#100
b1010 !
b1010 %
b10000000000 "
b10000000000 $
b1010 #
#110
b1011 !
b1011 %
b100000000000 "
b100000000000 $
b1011 #
#120
b1100 !
b1100 %
b1000000000000 "
b1000000000000 $
b1100 #
#130
b1101 !
b1101 %
b10000000000000 "
b10000000000000 $
b1101 #
#140
b1110 !
b1110 %
b100000000000000 "
b100000000000000 $
b1110 #
#150
b1111 #
